ullr/__init__.py
ullr/__main__.py
ullr/_configure.py
ullr/autoupdate.py
ullr/device_bus.py
ullr/getmac.py
ullr/local_device.py
ullr/mqtt_client.py
ullr/remote_device.py
ullr/session.py
ullr/settings.py
ullr/utils.py
ullr/cli/__init__.py
ullr/cli/cli.py
ullr/cli/interface.py
ullr/skiracetiming/__init__.py
ullr/skiracetiming/resequence.py
ullr/skiracetiming/translate.py
ullr/webapp/__init__.py
ullr/webapp/socketing.py
ullr/webapp/views.py
ullr/webapp/static/favicon.ico
ullr/webapp/static/jquery-3.6.0.min.js
ullr/webapp/static/site.css
ullr/webapp/static/site.js
ullr/webapp/static/socket.io.min-4.5.0.js
ullr/webapp/templates/home.html
Ullr-0.1.17.dist-info/LICENSE
Ullr-0.1.17.dist-info/METADATA
Ullr-0.1.17.dist-info/WHEEL
Ullr-0.1.17.dist-info/entry_points.txt
Ullr-0.1.17.dist-info/top_level.txt
Ullr-0.1.17.dist-info/RECORD
