Metadata-Version: 2.1
Name: Ullr
Version: 0.1.17
Summary: A serial <-> MQTT interface for sports timing.
Home-page: https://ullr.rtfd.io
Author: Zach Henry
Author-email: zhenry9@gmail.com
Classifier: Programming Language :: Python :: 3
Classifier: Development Status :: 3 - Alpha
Classifier: Intended Audience :: Developers
Classifier: License :: OSI Approved :: GNU General Public License (GPL)
Classifier: Natural Language :: English
Requires-Python: >=3.6
License-File: LICENSE
Requires-Dist: astroid (~=2.8.5)
Requires-Dist: bidict (~=0.21.4)
Requires-Dist: certifi (~=2021.10.8)
Requires-Dist: chardet (~=4.0.0)
Requires-Dist: charset-normalizer (~=2.0.7)
Requires-Dist: click (~=8.0.3)
Requires-Dist: colorama (~=0.4.4)
Requires-Dist: dnspython (~=2.1.0)
Requires-Dist: docopt (~=0.6.2)
Requires-Dist: Flask (~=2.0.2)
Requires-Dist: Flask-SocketIO (~=5.1.1)
Requires-Dist: idna (~=3.3)
Requires-Dist: importlib-metadata (~=4.8.2)
Requires-Dist: isort (~=5.10.1)
Requires-Dist: itsdangerous (~=2.0.1)
Requires-Dist: Jinja2 (~=3.0.3)
Requires-Dist: lazy-object-proxy (~=1.6.0)
Requires-Dist: MarkupSafe (~=2.0.1)
Requires-Dist: mccabe (~=0.6.1)
Requires-Dist: ntplib (~=0.4.0)
Requires-Dist: paho-mqtt (~=1.6.1)
Requires-Dist: platformdirs (~=2.4.0)
Requires-Dist: psutil (~=5.8.0)
Requires-Dist: pylint (~=2.11.1)
Requires-Dist: pyserial (~=3.5)
Requires-Dist: python-engineio (~=4.3.0)
Requires-Dist: python-socketio (~=5.5.0)
Requires-Dist: requests (~=2.26.0)
Requires-Dist: six (~=1.16.0)
Requires-Dist: termcolor (~=1.1.0)
Requires-Dist: toml (~=0.10.2)
Requires-Dist: typed-ast (~=1.5.0)
Requires-Dist: typing-extensions (~=4.0.0)
Requires-Dist: urllib3 (~=1.26.7)
Requires-Dist: Werkzeug (~=2.0.2)
Requires-Dist: wrapt (~=1.13.3)
Requires-Dist: yarg (~=0.1.9)
Requires-Dist: zipp (~=3.6.0)
Requires-Dist: zope.event (~=4.5.0)
Requires-Dist: zope.interface (~=5.4.0)
